AUTHORS.rst
CONTRIBUTING.rst
HISTORY.rst
LICENSE
MANIFEST.in
README.rst
setup.cfg
setup.py
docs/Makefile
docs/authors.rst
docs/conf.py
docs/contributing.rst
docs/history.rst
docs/index.rst
docs/installation.rst
docs/make.bat
docs/readme.rst
docs/usage.rst
formbuilder_client/__init__.py
formbuilder_client/formbuilder_client.py
formbuilder_client.egg-info/PKG-INFO
formbuilder_client.egg-info/SOURCES.txt
formbuilder_client.egg-info/dependency_links.txt
formbuilder_client.egg-info/not-zip-safe
formbuilder_client.egg-info/requires.txt
formbuilder_client.egg-info/top_level.txt
tests/__init__.py
tests/test_formbuilder_client.py