Metadata-Version: 1.1
Name: formbuilder-client
Version: 0.1.0
Summary: client for formbuilder
Home-page: https://github.com/wwj718/formbuilder_client
Author: wenjiewu
Author-email: wuwenjie718@gmail.com
License: BSD license
Keywords: formbuilder_client
Platform: UNKNOWN
Classifier: Development Status :: 2 - Pre-Alpha
Classifier: Intended Audience :: Developers
Classifier: License :: OSI Approved :: BSD License
Classifier: Natural Language :: English
Classifier: Programming Language :: Python :: 2
Classifier: Programming Language :: Python :: 2.6
Classifier: Programming Language :: Python :: 2.7
Classifier: Programming Language :: Python :: 3
Classifier: Programming Language :: Python :: 3.3
Classifier: Programming Language :: Python :: 3.4
Classifier: Programming Language :: Python :: 3.5
